high_precision_timer-2.0.0.dist-info/RECORD
high_precision_timer-2.0.0.dist-info/WHEEL
high_precision_timer-2.0.0.dist-info/entry_points.txt
high_precision_timer-2.0.0.dist-info/METADATA
high_precision_timer-2.0.0.dist-info/licenses/LICENSE
high_precision_timer/precision_timer_ext.abi3.so
high_precision_timer/precision_timer/timer_class.pyi
high_precision_timer/precision_timer/utilities.pyi
high_precision_timer/precision_timer/__init__.pyi
high_precision_timer/precision_timer/timer_benchmark.py
high_precision_timer/precision_timer/__init__.py
high_precision_timer/precision_timer/timer_benchmark.pyi
high_precision_timer/precision_timer/utilities.py
high_precision_timer/precision_timer/timer_class.py
