Metadata-Version: 2.1
Name: high-precision-timer
Version: 2.0.0
Summary: A sub-microsecond-precise timer for timing and delaying code execution in python with/out blocking.
Keywords: time,sub-microsecond,high precision,timer,elapsed,delay,time conversion,non-blocking
Author-Email: Ivan Kondratyev <ik278@cornell.edu>
Maintainer-Email: Ivan Kondratyev <ik278@cornell.edu>
License:                     GNU GENERAL PUBLIC LICENSE
Classifier: Development Status :: 5 - Production/Stable
Classifier: Intended Audience :: Developers
Classifier: Topic :: Software Development
Classifier: License :: OSI Approved :: GNU General Public License v3 or later (GPLv3+)
Classifier: Programming Language :: Python :: 3.10
Classifier: Programming Language :: Python :: 3.11
Classifier: Programming Language :: Python :: 3.12
Classifier: Programming Language :: C++
Classifier: Operating System :: Microsoft :: Windows
Classifier: Operating System :: POSIX :: Linux
Classifier: Operating System :: MacOS :: MacOS X
Project-URL: Homepage, https://github.com/Sun-Lab-NBB/HighPrecisionTimer
Project-URL: Documentation, https://high-precision-timer-docs.netlify.app/
Requires-Python: >=3.10
Requires-Dist: numpy
Requires-Dist: click
Requires-Dist: tqdm
Requires-Dist: mypy; extra == "lint"
Requires-Dist: ruff; extra == "lint"
Requires-Dist: types-tqdm; extra == "lint"
Requires-Dist: pytest; extra == "test"
Requires-Dist: pytest-cov; extra == "test"
Requires-Dist: pytest-xdist; extra == "test"
Requires-Dist: coverage[toml]; extra == "test"
Requires-Dist: sphinx; extra == "doc"
Requires-Dist: importlib_metadata; extra == "doc"
Requires-Dist: breathe; extra == "doc"
Requires-Dist: sphinx-rtd-theme; extra == "doc"
Requires-Dist: sphinx-click; extra == "doc"
Requires-Dist: scikit-build-core; extra == "build"
Requires-Dist: nanobind; extra == "build"
Requires-Dist: cibuildwheel; extra == "build"
Requires-Dist: tox; extra == "dev"
Requires-Dist: high-precision-timer[lint]; extra == "dev"
Requires-Dist: high-precision-timer[test]; extra == "dev"
Requires-Dist: high-precision-timer[doc]; extra == "dev"
Requires-Dist: high-precision-timer[build]; extra == "dev"
Provides-Extra: lint
Provides-Extra: test
Provides-Extra: doc
Provides-Extra: build
Provides-Extra: dev
